setup.py
tempfile.py
micropython_tempfile.egg-info/PKG-INFO
micropython_tempfile.egg-info/SOURCES.txt
micropython_tempfile.egg-info/dependency_links.txt
micropython_tempfile.egg-info/top_level.txt